Workbook

Sheet Overview
A1: 大阪觀光數據 AI 機器人 — 日系業者 100 題 FAQ 測試集
A3: 用途 | B3: Mike 機器人 PoC 測試題庫 / 提案附錄能力示範
A4: 對象 | B4: 準備進入大阪市場的日系業者(餐飲、零售、住宿、體驗、服務業)
A5: 資料來源 | B5: 大阪觀光局 datahub (data_01 旅マエ / data_02 海外見込み / data_03 旅ナカ・旅アト)
A6: 題數 | B6: 100 題 × 10 個決策階段
A8: 檔案結構
A9: 分頁名稱 | B9: 用途 | C9: 使用者
A10: Overview | B10: 本說明頁(你正在看的這頁) | C10: 人類閱讀
A11: FAQ_Data | B11: 主資料表,100 列扁平結構 | C11: AI / RAG 系統直接吃
A12: Stage_Summary | B12: 10 個階段的題數與評分統計 | C12: 人類閱讀 / Demo 參考
A13: Field_Definition | B13: 欄位定義說明 | C13: Mike / 工程端參考
A15: 數據標記規則
A16: [實數] | B16: 已從旅マエ基本集計取得、可直接使用
A17: [模擬] | B17: 需以 data_03 實際數據替換
A19: AI 餵食使用建議
A20: 1. RAG 灌庫 | B20: 讀取 FAQ_Data 分頁,每列為一筆 chunk,可用 question + answer_direction 欄位向量化
A21: 2. 測試集評估 | B21: 用 question_variants 欄位生成多種使用者問法,跑機器人輸出,比對 answer_direction 與 source 是否命中
A22: 3. Prompt 工程 | B22: 用 stage + business_value 欄位作為 few-shot 範例選擇依據
A24: 評分加總
A25: 70% (350+ / 500) | B25: 可用門檻
A26: 80% (400+ / 500) | B26: 提案 Demo 等級
A27: 90% (450+ / 500) | B27: 上線等級

Sheet FAQ_Data
A1: id | B1: stage_no | C1: stage_name | D1: question | E1: question_jp | F1: question_zh_variant | G1: question_en_variant | H1: answer_direction | I1: key_data_points | J1: data_source_primary | K1: data_source_secondary | L1: data_type | M1: business_value | N1: scoring_criteria | O1: max_score | P1: test_priority | Q1: is_boundary_test | R1: is_demo_question
A2: Q1 | B2: 1 | C2: 市場規模判斷 | D2: 大阪每年外國旅客總量?前三大市場? | E2: 大阪のインバウンドは年間何人?トップ3市場は? | F2: 大阪一年來多少外國觀光客? | G2: How many foreign tourists visit Osaka annually? Top 3 markets? | H2: 大阪在 2023 年度接待約 1,247 萬人次外國旅客,較疫前 2019 年回復至約 94%。前三大客源:韓國 26%、中國 22%、台灣 17%。亞洲市場合計超過 80%。 | I2: 總人次、前三市場排序、復甦比例 | J2: 來阪外國人旅遊者數推計 | K2: 訪日外國人關西國際空港出口調查 | L2: 模擬 | M2: 確認目標客群是否在市場規模內 | N2: 總量數字+前三排序+年份+復甦對比+報告連結 | O2: 5 | P2: smoke | Q2: N | R2: N
A3: Q2 | B3: 1 | C3: 市場規模判斷 | D3: 大阪外國旅客近三年成長趨勢? | E3: コロナ後の回復はどう? | F3: 成長中還是衰退中? | G3: Recent 3-year growth trend? | H3: 2021→2023 年大阪外國旅客呈強勁回復,整體年增率約 +XX%。最快復甦市場為東南亞(疫後超越疫前)、最慢為中國市場(政策影響)。 | I3: 趨勢方向、年增率、識別異常成長市場 | J3: 來阪外國人旅遊者數推計(時序) | L3: 模擬 | M3: 判斷市場進場時機 | N3: 趨勢方向+年增率+異常成長市場識別 | O3: 5 | P3: standard | Q3: N | R3: N
A4: Q3 | B4: 1 | C4: 市場規模判斷 | D4: 大阪 vs 東京 vs 京都,外國旅客誰多? | E4: 大阪・東京・京都の比較は? | F4: 想進關西市場,大阪比較有量還是京都? | G4: Osaka vs Tokyo vs Kyoto in tourist volume? | H4: 東京年外國旅客約 X 萬 > 大阪 1,247 萬 > 京都 X 萬。但結構差異大:京都多為日歸(含住大阪)、大阪過夜比例高、東京商務+觀光雙軌。 | I4: 三都量對比、結構差異 | J4: datahub + 全國觀光統計 | L4: 模擬 | M4: 三都選擇判斷 | N4: 三都對比+為什麼選大阪的觀點 | O4: 5 | P4: standard | Q4: N | R4: N
A5: Q4 | B5: 1 | C5: 市場規模判斷 | D5: 大阪外國旅客過夜 vs 日歸比例? | E5: 宿泊客と日帰り客の比率は? | F5: 過夜的多還是日歸的多? | G5: Overnight vs day-trip ratio? | H5: 外國旅客過夜比例約 X%、平均住宿天數 X 晚。京都旅客常住大阪、放大大阪住宿經濟圈。 | I5: 過夜比例、平均住宿天數 | J5: 訪日外國人關西空港出口調查 | L5: 模擬 | M5: 住宿/餐飲業規劃 | N5: 比例+平均天數+住宿經濟圈解讀 | O5: 5 | P5: standard | Q5: N | R5: N
A6: Q5 | B6: 1 | C6: 市場規模判斷 | D6: 外國旅客在大阪平均消費金額? | E6: 外国人観光客の一人当たり消費額は? | F6: 外國客平均花多少錢? | G6: Average spending per foreign tourist? | H6: 外國旅客一人在大阪平均消費 X 万円。歐美市場 > 亞洲市場;品類占比:住宿 X%、餐飲 X%、購物 X%、娛樂 X%。 | I6: 總額、市場差異、品類拆解 | J6: 訪日旅客消費調查 | L6: 模擬 | M6: 客單價設定基準 | N6: 總額+市場差異+品類拆解 | O6: 5 | P6: standard | Q6: N | R6: N
A7: Q6 | B7: 1 | C7: 市場規模判斷 | D7: 哪國旅客平均消費最高? | E7: 客単価が一番高い国は? | F7: 想做高端,鎖定哪國最好? | G7: Which market spends the most per capita? | H7: 客單價排行:澳洲 > 英國 > 美國 > 法國 > 加拿大。與量大市場(韓中)區隔:量大客群 vs 值高客群。 | I7: 客單價排行、量 vs 值區隔 | J7: 訪日旅客消費調查 | L7: 模擬 | M7: 高端業者鎖定客群 | N7: 客單價排行+量值區隔策略 | O7: 5 | P7: standard | Q7: Y | R7: N
A8: Q7 | B8: 1 | C8: 市場規模判斷 | D8: 大阪過夜旅客平均停留天數? | E8: 平均何泊? | F8: 外國客在大阪通常住幾天? | G8: Average stay nights? | H8: 外國旅客平均停留 X 晚。歐美 > 亞洲(歐美一趟通常 2 週、亞洲短假 3-5 天為主)。 | I8: 平均天數、市場差異 | J8: 訪日外國人關西空港出口調查 | L8: 模擬 | M8: 體驗型業態時長設計 | N8: 天數+市場差異+業者意涵 | O8: 5 | P8: standard | Q8: N | R8: N
A9: Q8 | B9: 1 | C9: 市場規模判斷 | D9: 大阪外國旅客「第一次」vs「重遊」比例? | E9: リピーター比率は? | F9: 來大阪的是新手還是老手? | G9: First-timers vs repeaters? | H9: 重遊比例約 X%。重訪客行為:更深度、更分散、更省預算;初訪客集中知名景點。 | I9: 比例、行為差異 | J9: 旅マエ海外市場調查 | K9: 出口調查 | L9: 模擬 | M9: 深度體驗業 vs 標準觀光業選擇 | N9: 比例+行為差異+業者意涵 | O9: 5 | P9: standard | Q9: N | R9: N
A10: Q9 | B10: 1 | C10: 市場規模判斷 | D10: 大阪國內旅客量?跟外國旅客比? | E10: 国内観光客の規模は? | F10: 日本國內客有多少? | G10: Domestic tourist volume? | H10: 國內年旅客 X 萬人次 vs 外國 1,247 萬。國內客分布:關西內 X%、關東 X%、其他 X%。 | I10: 國內外比例、地區分布 | J10: 大阪版國內觀光統計調查 | L10: 模擬 | M10: 提醒不要只看觀光客 | N10: 總量+內外比例+提醒平衡策略 | O10: 5 | P10: standard | Q10: N | R10: N
A11: Q10 | B11: 1 | C11: 市場規模判斷 | D11: 進大阪市場整體成本/門檻概況? | E11: 大阪で店出すコスト感は? | F11: 進大阪市場的綜合成本怎麼樣? | G11: Overall market entry cost? | H11: 這是 datahub 資料範圍外的問題。datahub 為觀光/旅客數據平台,商業成本資訊建議查詢 JETRO、大阪商工會議所、不動產協會等資源。 | I11: 明確說明邊界 | J11: 無 — 邊界外題 | L11: 邊界外 | M11: 測試機器人會不會誠實說『答不出來』 | N11: 不亂答+明確邊界+給延伸方向 | O11: 5 | P11: edge | Q11: Y | R11: Y
A12: Q11 | B12: 2 | C12: 客群選擇 | D12: 哪國旅客對在地飲食興趣最高? | E12: ローカルフードに興味がある国は? | F12: 外國人最想吃什麼? | G12: Which market is most interested in local food? | H12: 在地飲食活動興趣 7.86/10 居所有活動首位(資料:旅マエ基本集計)。市場差異:亞洲對屋台 B 級美食、歐美對高級餐廳興趣較高。 | I12: 興趣度實數、市場差異 | J12: 旅マエ海外市場調查(基本集計) | L12: 實數 | M12: 餐飲業客群鎖定 | N12: 實數+市場差異+業態建議 | O12: 5 | P12: smoke | Q12: Y | R12: Y
A13: Q12 | B13: 2 | C13: 客群選擇 | D13: 哪國旅客對購物最積極? | E13: ショッピング目的の国は? | F13: 誰來大阪是為了買東西? | G13: Most shopping-driven markets? | H13: 中國、韓國市場購物消費比重高。品類差異:中國重藥妝/精品、韓國重時尚/雜貨、東南亞重伴手禮。 | I13: 市場排序、品類差異 | J13: 旅マエ海外市場調查 | K13: 消費調查 | L13: 模擬 | M13: 零售業客群鎖定 | N13: 市場排序+品類差異 | O13: 5 | P13: standard | Q13: N | R13: N
A14: Q13 | B14: 2 | C14: 客群選擇 | D14: 哪國旅客對夜間經濟興趣高? | E14: ナイトライフ需要の国は? | F14: 夜店、夜景需求最強的市場? | G14: Nightlife-oriented markets? | H14: 夜景/照明興趣度 7.05/10(資料:旅マエ)。歐美 + 東南亞市場夜間活動需求較高。 | I14: 夜間活動實數、市場差異 | J14: 旅マエ海外市場調查 | L14: 實數 | M14: 酒吧/夜景甜點業態 | N14: 活動分數+市場差異 | O14: 5 | P14: standard | Q14: N | R14: N
A15: Q14 | B15: 2 | C15: 客群選擇 | D15: 哪國旅客家庭/親子客比例高? | E15: ファミリー層が多いのは? | F15: 家庭客主要來自哪國? | G15: Family-tourist heavy markets? | H15: 家族同行(含 17 歲以下)28.7%(實數,旅マエ)。東南亞、台灣家庭客比例高。 | I15: 家族比例實數、市場差異 | J15: 旅マエ海外市場調查 — 同行者 | L15: 實數 | M15: 親子業態客群 | N15: 比例+市場+親子業態建議 | O15: 5 | P15: standard | Q15: N | R15: N
A16: Q15 | B16: 2 | C16: 客群選擇 | D16: 哪國旅客是 Z 世代主力? | E16: 若年層インバウンドはどこの国? | F16: 年輕客群來自哪國? | G16: Z-gen/young tourist markets? | H16: 20-29 歲合計 11.7%(實數,旅マエ)。台灣、韓國、東南亞年輕客占比較高,SNS 依賴度極高。 | I16: 年齡結構、市場差異 | J16: 旅マエ海外市場調查 — 年齡 | L16: 實數 | M16: 年輕客業態行銷 | N16: 年齡結構+市場+SNS 行為 | O16: 5 | P16: standard | Q16: N | R16: N
A17: Q16 | B17: 2 | C17: 客群選擇 | D17: 哪國旅客 LGBTQ+ 友善需求顯著? | E17: LGBTQ+ フレンドリーマーケットは? | F17: LGBTQ+ 客群來自哪些市場? | G17: LGBTQ+ friendly market needs? | H17: 歐美主要市場(英、美、加、澳、荷)LGBTQ+ 旅客比例高。大阪觀光局已有 LGBTQ+ 旅客專項調查(2024)。 | I17: 市場別比例、專項調查引用 | J17: 大阪 LGBTQ+ 旅遊者動向調查 2024 | L17: 模擬 | M17: 包容性業態設計 | N17: 市場+專項調查+友善設計 | O17: 5 | P17: standard | Q17: N | R17: N
A18: Q17 | B18: 2 | C18: 客群選擇 | D18: 哪國旅客素食/清真/過敏需求高? | E18: ハラル・ヴィーガン対応必要な国は? | F18: 需要素食/清真對應的市場? | G18: Halal/vegan demand markets? | H18: 印尼、馬來西亞、印度(穆斯林市場)為清真主要需求;歐美素食/純素需求穩定。 | I18: 市場區隔、需求類型 | J18: 旅マエ海外市場調查 | L18: 模擬 | M18: 餐飲業特殊餐區隔 | N18: 市場+需求類型+業者意涵 | O18: 5 | P18: standard | Q18: N | R18: N
A19: Q18 | B19: 2 | C19: 客群選擇 | D19: 哪國旅客動漫/IP 文化興趣最高? | E19: アニメ・ポップカルチャー目的は? | F19: 動漫迷主要來自哪國? | G19: Anime/pop culture market? | H19: IP 商品店巡禮、主題咖啡興趣度約 6.4-6.8。東南亞、台、韓、歐美年輕客興趣顯著。 | I19: 興趣度、市場分布 | J19: 旅マエ海外市場調查 — 活動興趣 | L19: 實數 | M19: IP 業態客群 | N19: 興趣度+市場+業態建議 | O19: 5 | P19: standard | Q19: N | R19: N
A20: Q19 | B20: 2 | C20: 客群選擇 | D20: 哪國旅客美容/醫美消費比重高? | E20: 美容医療目的の市場は? | F20: 醫美客主要來自哪國? | G20: Medical beauty tourism market? | H20: 中國、台灣、韓國市場美容醫美消費活躍,常為「附帶觀光行程」。 | I20: 市場排序、消費規模 | J20: 訪日旅客消費調查 — 品類 | L20: 模擬 | M20: 醫美延伸業態(術後甜點/SPA) | N20: 市場+消費規模+業態 | O20: 5 | P20: standard | Q20: N | R20: N
A21: Q20 | B21: 2 | C21: 客群選擇 | D21: 重遊客 vs 初訪客行動差異? | E21: リピーターと初訪の行動差は? | F21: 回頭客跟新客行為差在哪? | G21: Repeat vs first-time tourist behavior? | H21: 初訪集中知名景點(USJ、城、道頓堀);重訪深度體驗、周邊市町、隱藏景點。 | I21: 差異描述、業態意涵 | J21: 出口調查 / 旅マエ | L21: 模擬 | M21: 深度業態 = 重訪客藍海 | N21: 差異+業者藍海解讀 | O21: 5 | P21: core | Q21: N | R21: N
A22: Q21 | B22: 3 | C22: 選址判斷 | D22: 心齋橋 vs 道頓堀 vs 難波,旅客到訪率? | E22: 心斎橋・道頓堀・難波の比較 | F22: 三區人潮哪邊多? | G22: Shinsaibashi vs Dotonbori vs Namba foot traffic? | H22: 道頓堀 68% > 心齋橋 61% > 難波 49%(模擬)。行為截然不同:道頓堀=打卡型、心齋橋=逛街型、難波=過路型。 | I22: 三區數字、行為差異 | J22: 觀光地點參數調查 2024 | L22: 模擬 | M22: 選址初篩 | N22: 三區數字+行為差異+選址提醒 | O22: 5 | P22: core | Q22: Y | R22: Y
A23: Q22 | B23: 3 | C23: 選址判斷 | D23: 梅田 vs 心齋橋,業者該選哪邊? | E23: 梅田と心斎橋、出店するなら? | F23: 兩區選一個開店? | G23: Umeda vs Shinsaibashi for new shop? | H23: 梅田=商務+國內客+通勤;心齋橋=觀光客+衝動消費。依業態而定。 | I23: 差異對比、依業態建議 | J23: 觀光地點參數調查 | L23: 模擬 | M23: 兩大商圈業者抉擇 | N23: 差異對比+業態依存 | O23: 5 | P23: standard | Q23: N | R23: N
A24: Q23 | B24: 3 | C24: 選址判斷 | D24: USJ 周邊外國旅客特徵? | E24: USJ 周辺の客層は? | F24: 環球影城旁的客群長什麼樣? | G24: USJ area tourist profile? | H24: 家族親子比例高、停留短、客單高、餐飲與紀念品需求集中。 | I24: 客層描述、業態適配 | J24: 觀光地點參數調查 — USJ 區 | L24: 模擬 | M24: USJ 周邊選址判斷 | N24: 客層+業態適配建議 | O24: 5 | P24: standard | Q24: N | R24: N
A25: Q24 | B25: 3 | C25: 選址判斷 | D25: 大阪城公園周邊外國旅客比例? | E25: 大阪城エリアのインバウンド比率は? | F25: 大阪城旁外國人多嗎? | G25: Osaka Castle area inbound ratio? | H25: 外國旅客比例高、停留 1.5-2 小時、消費較低,適合輕食/紀念品/體驗。 | I25: 比例、停留、消費水準 | J25: 觀光地點參數調查 — 大阪城區 | L25: 模擬 | M25: 短停留型業態 | N25: 比例+時長+業態建議 | O25: 5 | P25: standard | Q25: N | R25: N
... A101: Q100 | B101: 10 | C101: 進階交叉 | D101: 你的資料是哪一年的?可信嗎? | E101: データの信頼性と更新頻度は? | F101: 資料什麼時候的?可不可信? | G101: What years is your data from? Reliable? | H101: 明確列出各資料源年份、來源機構、更新頻率。透明度=信賴度,合規與信賴的核心。 | I101: 主動透明資料邊界 | J101: datahub 各報告 metadata | L101: 邊界外 | M101: 合規與信賴核心 | N101: 完整透明+來源年份 | O101: 6 | P101: edge | Q101: Y | R101: Y

Sheet Stage_Summary
A1: stage_no | B1: stage_name | C1: 題數 | D1: 滿分總和 | E1: smoke | F1: core | G1: edge | H1: demo_questions
A2: 1 | B2: 市場規模判斷 | C2: =COUNTIF(FAQ_Data!B:B,1) -> 10 | D2: =SUMIF(FAQ_Data!B:B,1,FAQ_Data!O:O) -> 50 | E2: =COUNTIFS(FAQ_Data!B:B,1,FAQ_Data!P:P,"smoke") -> 1 | F2: =COUNTIFS(FAQ_Data!B:B,1,FAQ_Data!P:P,"core") -> 0 | G2: =COUNTIFS(FAQ_Data!B:B,1,FAQ_Data!P:P,"edge") -> 1 | H2: =COUNTIFS(FAQ_Data!B:B,1,FAQ_Data!R:R,"Y") -> 1
A3: 2 | B3: 客群選擇 | C3: =COUNTIF(FAQ_Data!B:B,2) -> 10 | D3: =SUMIF(FAQ_Data!B:B,2,FAQ_Data!O:O) -> 50 | E3: =COUNTIFS(FAQ_Data!B:B,2,FAQ_Data!P:P,"smoke") -> 1 | F3: =COUNTIFS(FAQ_Data!B:B,2,FAQ_Data!P:P,"core") -> 1 | G3: =COUNTIFS(FAQ_Data!B:B,2,FAQ_Data!P:P,"edge") -> 0 | H3: =COUNTIFS(FAQ_Data!B:B,2,FAQ_Data!R:R,"Y") -> 1
A4: 3 | B4: 選址判斷 | C4: =COUNTIF(FAQ_Data!B:B,3) -> 10 | D4: =SUMIF(FAQ_Data!B:B,3,FAQ_Data!O:O) -> 50 | E4: =COUNTIFS(FAQ_Data!B:B,3,FAQ_Data!P:P,"smoke") -> 0 | F4: =COUNTIFS(FAQ_Data!B:B,3,FAQ_Data!P:P,"core") -> 3 | G4: =COUNTIFS(FAQ_Data!B:B,3,FAQ_Data!P:P,"edge") -> 0 | H4: =COUNTIFS(FAQ_Data!B:B,3,FAQ_Data!R:R,"Y") -> 1
A5: 4 | B5: 業態設計 | C5: =COUNTIF(FAQ_Data!B:B,4) -> 10 | D5: =SUMIF(FAQ_Data!B:B,4,FAQ_Data!O:O) -> 51 | E5: =COUNTIFS(FAQ_Data!B:B,4,FAQ_Data!P:P,"smoke") -> 1 | F5: =COUNTIFS(FAQ_Data!B:B,4,FAQ_Data!P:P,"core") -> 3 | G5: =COUNTIFS(FAQ_Data!B:B,4,FAQ_Data!P:P,"edge") -> 0 | H5: =COUNTIFS(FAQ_Data!B:B,4,FAQ_Data!R:R,"Y") -> 4
A6: 5 | B6: 行銷通路 | C6: =COUNTIF(FAQ_Data!B:B,5) -> 10 | D6: =SUMIF(FAQ_Data!B:B,5,FAQ_Data!O:O) -> 50 | E6: =COUNTIFS(FAQ_Data!B:B,5,FAQ_Data!P:P,"smoke") -> 1 | F6: =COUNTIFS(FAQ_Data!B:B,5,FAQ_Data!P:P,"core") -> 1 | G6: =COUNTIFS(FAQ_Data!B:B,5,FAQ_Data!P:P,"edge") -> 0 | H6: =COUNTIFS(FAQ_Data!B:B,5,FAQ_Data!R:R,"Y") -> 2
A7: 6 | B7: 定價策略 | C7: =COUNTIF(FAQ_Data!B:B,6) -> 10 | D7: =SUMIF(FAQ_Data!B:B,6,FAQ_Data!O:O) -> 50 | E7: =COUNTIFS(FAQ_Data!B:B,6,FAQ_Data!P:P,"smoke") -> 1 | F7: =COUNTIFS(FAQ_Data!B:B,6,FAQ_Data!P:P,"core") -> 1 | G7: =COUNTIFS(FAQ_Data!B:B,6,FAQ_Data!P:P,"edge") -> 1 | H7: =COUNTIFS(FAQ_Data!B:B,6,FAQ_Data!R:R,"Y") -> 0
A8: 7 | B8: 營運服務 | C8: =COUNTIF(FAQ_Data!B:B,7) -> 10 | D8: =SUMIF(FAQ_Data!B:B,7,FAQ_Data!O:O) -> 50 | E8: =COUNTIFS(FAQ_Data!B:B,7,FAQ_Data!P:P,"smoke") -> 0 | F8: =COUNTIFS(FAQ_Data!B:B,7,FAQ_Data!P:P,"core") -> 1 | G8: =COUNTIFS(FAQ_Data!B:B,7,FAQ_Data!P:P,"edge") -> 0 | H8: =COUNTIFS(FAQ_Data!B:B,7,FAQ_Data!R:R,"Y") -> 0
A9: 8 | B9: 競合分析 | C9: =COUNTIF(FAQ_Data!B:B,8) -> 10 | D9: =SUMIF(FAQ_Data!B:B,8,FAQ_Data!O:O) -> 50 | E9: =COUNTIFS(FAQ_Data!B:B,8,FAQ_Data!P:P,"smoke") -> 0 | F9: =COUNTIFS(FAQ_Data!B:B,8,FAQ_Data!P:P,"core") -> 3 | G9: =COUNTIFS(FAQ_Data!B:B,8,FAQ_Data!P:P,"edge") -> 0 | H9: =COUNTIFS(FAQ_Data!B:B,8,FAQ_Data!R:R,"Y") -> 2
A10: 9 | B10: 風險時機 | C10: =COUNTIF(FAQ_Data!B:B,9) -> 10 | D10: =SUMIF(FAQ_Data!B:B,9,FAQ_Data!O:O) -> 50 | E10: =COUNTIFS(FAQ_Data!B:B,9,FAQ_Data!P:P,"smoke") -> 0 | F10: =COUNTIFS(FAQ_Data!B:B,9,FAQ_Data!P:P,"core") -> 2 | G10: =COUNTIFS(FAQ_Data!B:B,9,FAQ_Data!P:P,"edge") -> 2 | H10: =COUNTIFS(FAQ_Data!B:B,9,FAQ_Data!R:R,"Y") -> 0
A11: 10 | B11: 進階交叉 | C11: =COUNTIF(FAQ_Data!B:B,10) -> 10 | D11: =SUMIF(FAQ_Data!B:B,10,FAQ_Data!O:O) -> 58 | E11: =COUNTIFS(FAQ_Data!B:B,10,FAQ_Data!P:P,"smoke") -> 0 | F11: =COUNTIFS(FAQ_Data!B:B,10,FAQ_Data!P:P,"core") -> 5 | G11: =COUNTIFS(FAQ_Data!B:B,10,FAQ_Data!P:P,"edge") -> 5 | H11: =COUNTIFS(FAQ_Data!B:B,10,FAQ_Data!R:R,"Y") -> 5
B12: 總計 | C12: =SUM(C2:C11) -> 100 | D12: =SUM(D2:D11) -> 509 | E12: =SUM(E2:E11) -> 5 | F12: =SUM(F2:F11) -> 20 | G12: =SUM(G2:G11) -> 9 | H12: =SUM(H2:H11) -> 16
A15: 評分門檻
B16: 70% 可用門檻 | C16: =ROUND(D12*0.7,0) -> 356
B17: 80% Demo 等級 | C17: =ROUND(D12*0.8,0) -> 407
B18: 90% 上線等級 | C18: =ROUND(D12*0.9,0) -> 458

Sheet Field_Definition
A1: 欄位名稱 | B1: 中文說明 | C1: 用途 | D1: AI 使用建議
A2: id | B2: 題號 | C2: Q1 ~ Q100 唯一識別 | D2: 可作為 RAG chunk 的 metadata
A3: stage_no | B3: 階段編號 1-10 | C3: 業者決策旅程階段 | D3: 用於分層檢索
A4: stage_name | B4: 階段名稱 | C4: 可讀性標籤 | D4: 向量化時可加權
A5: question | B5: 主題問題(中文) | C5: 核心查詢意圖 | D5: 主要 embedding 來源
A6: question_jp | B6: 業者日文問法 | C6: 日文場景測試 | D6: 日文版 embedding
A7: question_zh_variant | B7: 中文問法變體 | C7: 口語化變體 | D7: 擴展訓練語料
A8: question_en_variant | B8: 英文問法變體 | C8: 英文場景測試 | D8: 英文版 embedding
A9: answer_direction | B9: AI 回答方向 | C9: 完整回答模板 | D9: 輸出比對基準
A10: key_data_points | B10: 必含關鍵數據點 | C10: 驗收必含內容 | D10: rubric 評分依據
A11: data_source_primary | B11: 主要資料源 | C11: RAG 必引用報告 | D11: 檢索目標報告
A12: data_source_secondary | B12: 次要資料源 | C12: 輔助資料 | D12: 交叉查詢依據
... A19: is_demo_question | B19: Y/N - 是否 Demo 展示題 | C19: 提案展示用 | D19: 提案 Demo 選題
